vsgen/__init__.py
vsgen/__main__.py
vsgen/api.py
vsgen/cli/__init__.py
vsgen/cli/_pathconfig.py
vsgen/cli/generate.py
vsgen/cli/project.py
vsgen/cli/solution.py
vsgen/configfile.py
vsgen/configuration.py
vsgen/introspector.py
vsgen/runsettings.py
vsgen/sln.py
vsgen/vcxproj.py
meson_vs_gen-0.7.0.dist-info/LICENSE
meson_vs_gen-0.7.0.dist-info/METADATA
meson_vs_gen-0.7.0.dist-info/WHEEL
meson_vs_gen-0.7.0.dist-info/entry_points.txt
meson_vs_gen-0.7.0.dist-info/RECORD
