Metadata-Version: 2.3
Name: meson-vs-gen
Version: 0.7.0
Summary: Generates Visual Studio solutions and projects for meson projects
License: MIT
Keywords: visualstudio,meson
Author: Charles Brunet
Author-email: charles.brunet@optelgroup.com
Requires-Python: >=3.9,<4.0
Classifier: Development Status :: 3 - Alpha
Classifier: Environment :: Console
Classifier: Intended Audience :: Developers
Classifier: License :: OSI Approved :: MIT License
Classifier: Operating System :: OS Independent
Classifier: Programming Language :: Python :: 3
Classifier: Programming Language :: Python :: 3.9
Classifier: Programming Language :: Python :: 3.10
Classifier: Programming Language :: Python :: 3.11
Classifier: Programming Language :: Python :: 3.12
Classifier: Programming Language :: Python :: 3.13
Classifier: Topic :: Software Development :: Build Tools
Provides-Extra: test
Requires-Dist: cleo
Requires-Dist: lxml
Requires-Dist: meson (>=1.2.0,<2.0.0) ; extra == "test"
Requires-Dist: pytest ; extra == "test"
Requires-Dist: pyyaml
Project-URL: Bug Tracker, https://gitlab.com/optelgroup-public/meson-vs-gen/-/issues
Project-URL: Repository, https://gitlab.com/optelgroup-public/meson-vs-gen
